<?xml version="1.0" encoding="UTF-8"?>
<actor PGFVersion="0.17" id="id389466" GSCVersion="0.9.5"><attributes><text id="name">Background Active</text><real id="time">0</real><point id="position"><real id="x">0</real><real id="y">0</real></point><size id="size"><real id="width">500</real><real id="height">340</real></size><angle id="rotation">0</angle><color id="color"><real id="red">1</real><real id="green">1</real><real id="blue">1</real><real id="alpha">1</real></color><image id="image">Background</image><text id="tags"></text></attributes><behaviors><behavior id="id642500" class="PlayMusicAction" enabled="true"><attributes><text id="name">Play Music</text><text id="bundleName">PlayMusic.behavior</text><music id="musicName">Game Music</music><boolean id="loop">true</boolean></attributes></behavior><behavior enabled="true" id="id667482" class="RuleBehavior"><attributes><text id="name">Rule</text><text id="bundleName">Rule.behavior</text><real id="compoundConditionKind">0</real></attributes><conditions><condition id="id571105" eventType="mouse button"><attributes><index id="conditionType">1</index><text id="subjectAttribute">game.attributes.id142699</text></attributes><predicate type="number"><attributes><text id="operator">&gt;</text><real id="RHS">20</real></attributes></predicate></condition></conditions><behaviors><behavior id="id342150" class="ChangeSceneAction" enabled="true"><attributes><text id="name">Change Scene</text><text id="bundleName">ChangeScene.behavior</text><text id="sceneKey">id722548</text></attributes></behavior></behaviors><elseBehaviors/></behavior><behavior enabled="true" id="id819639" class="RuleBehavior"><attributes><text id="name">Rule</text><text id="bundleName">Rule.behavior</text><real id="compoundConditionKind">1</real></attributes><conditions><condition id="id347761" eventType="mouse button"><attributes><index id="conditionType">1</index><text id="subjectAttribute">game.attributes.id142699</text></attributes><predicate type="number"><attributes><text id="operator">=</text><real id="RHS">10</real></attributes></predicate></condition><condition id="id204150" eventType="mouse button"><attributes><index id="conditionType">1</index><text id="subjectAttribute">game.attributes.id142699</text></attributes><predicate type="number"><attributes><text id="operator">=</text><real id="RHS">20</real></attributes></predicate></condition></conditions><behaviors><behavior id="id111620" class="TimerBehavior" enabled="true"><attributes><text id="name">Timer</text><text id="bundleName">Timer.behavior</text><index id="timerType">1</index><real id="interval">0.5</real><boolean id="runToCompletion">false</boolean></attributes><behaviors><behavior id="id112082" class="SpawnAction" enabled="true"><attributes><text id="name">Spawn Actor</text><text id="bundleName">Spawn.behavior</text><text id="prototypeKey">id998284</text><angle id="direction">0</angle><index id="directionSpace">0</index><real id="x">0</real><real id="y">220</real><index id="positionSpace">0</index><index id="layerOrder">0</index></attributes></behavior></behaviors></behavior></behaviors><elseBehaviors/></behavior><behavior enabled="true" id="id380566" class="RuleBehavior"><attributes><text id="name">Rule</text><text id="bundleName">Rule.behavior</text><real id="compoundConditionKind">0</real></attributes><conditions><condition id="id549989" eventType="mouse button"><attributes><index id="conditionType">1</index><text id="subjectAttribute">game.attributes.id142699</text></attributes><predicate type="number"><attributes><text id="operator">!=</text><real id="RHS">10</real></attributes></predicate></condition></conditions><behaviors><behavior id="id812599" class="TimerBehavior" enabled="true"><attributes><text id="name">Timer</text><text id="bundleName">Timer.behavior</text><index id="timerType">0</index><real id="interval"><expression><reference keypath="game.attributes.id774859"/></expression></real><boolean id="runToCompletion">false</boolean></attributes><behaviors><behavior id="id969296" class="SpawnAction" enabled="true"><attributes><text id="name">Spawn Actor</text><text id="bundleName">Spawn.behavior</text><text id="prototypeKey">id792507</text><angle id="direction">0</angle><index id="directionSpace">0</index><real id="x"><expression><string>random(0,500)</string></expression></real><real id="y">350</real><index id="positionSpace">1</index><index id="layerOrder">0</index></attributes></behavior></behaviors></behavior></behaviors><elseBehaviors/></behavior><behavior id="id255786" class="TimerBehavior" enabled="true"><attributes><text id="name">Timer</text><text id="bundleName">Timer.behavior</text><index id="timerType">0</index><real id="interval">1</real><boolean id="runToCompletion">false</boolean></attributes><behaviors><behavior enabled="true" id="id729526" class="RuleBehavior"><attributes><text id="name">Rule</text><text id="bundleName">Rule.behavior</text><real id="compoundConditionKind">0</real></attributes><conditions><condition id="id344060" eventType="mouse button"><attributes><index id="conditionType">1</index><text id="subjectAttribute">game.attributes.id570381</text></attributes><predicate type="boolean"><attributes><index id="RHS">1</index></attributes></predicate></condition></conditions><behaviors><behavior id="id159007" class="ChangeAttributeAction" enabled="true"><attributes><text id="name">Change Attribute</text><text id="bundleName">ChangeAttribute.behavior</text><text id="targetAttribute">game.attributes.id759501</text><text id="RHS"><expression><reference keypath="game.attributes.id759501"/><string>+10</string></expression></text></attributes></behavior></behaviors><elseBehaviors/></behavior><behavior id="id305565" class="ChangeAttributeAction" enabled="true"><attributes><text id="name">Change Attribute</text><text id="bundleName">ChangeAttribute.behavior</text><text id="targetAttribute">game.attributes.id705553</text><text id="RHS"><expression><reference keypath="game.attributes.id705553"/><string>+</string><reference keypath="game.attributes.id866816"/></expression></text></attributes></behavior></behaviors></behavior><behavior enabled="true" id="id205992" class="RuleBehavior"><attributes><text id="name">Rule</text><text id="bundleName">Rule.behavior</text><real id="compoundConditionKind">0</real></attributes><conditions><condition id="id991170" eventType="mouse button"><attributes><index id="conditionType">1</index><text id="subjectAttribute">game.attributes.id113566</text></attributes><predicate type="number"><attributes><text id="operator">=</text><real id="RHS">0</real></attributes></predicate></condition></conditions><behaviors><behavior id="id816364" class="TimerBehavior" enabled="true"><attributes><text id="name">Timer</text><text id="bundleName">Timer.behavior</text><index id="timerType">1</index><real id="interval">1</real><boolean id="runToCompletion">false</boolean></attributes><behaviors><behavior id="id741724" class="SpawnAction" enabled="true"><attributes><text id="name">Spawn Actor</text><text id="bundleName">Spawn.behavior</text><text id="prototypeKey">id700442</text><angle id="direction">0</angle><index id="directionSpace">0</index><real id="x">0</real><real id="y">0</real><index id="positionSpace">0</index><index id="layerOrder">0</index></attributes></behavior></behaviors></behavior><behavior id="id816979" class="ChangeAttributeAction" enabled="true"><attributes><text id="name">Change Attribute</text><text id="bundleName">ChangeAttribute.behavior</text><text id="targetAttribute">game.attributes.id621621</text><text id="RHS"><expression><reference keypath="game.attributes.id621621"/><string>+15</string></expression></text></attributes></behavior><behavior id="id636444" class="ChangeAttributeAction" enabled="true"><attributes><text id="name">Change Attribute</text><text id="bundleName">ChangeAttribute.behavior</text><text id="targetAttribute">game.attributes.id774859</text><text id="RHS"><expression><reference keypath="game.attributes.id774859"/><string>-0.2</string></expression></text></attributes></behavior><behavior id="id455437" class="ChangeAttributeAction" enabled="true"><attributes><text id="name">Change Attribute</text><text id="bundleName">ChangeAttribute.behavior</text><text id="targetAttribute">game.attributes.id142699</text><text id="RHS"><expression><reference keypath="game.attributes.id142699"/><string>+1</string></expression></text></attributes></behavior><behavior id="id986070" class="ChangeSceneAction" enabled="true"><attributes><text id="name">Change Scene</text><text id="bundleName">ChangeScene.behavior</text><text id="sceneKey">next</text></attributes></behavior><behavior id="id423864" class="ChangeAttributeAction" enabled="true"><attributes><text id="name">Change Attribute</text><text id="bundleName">ChangeAttribute.behavior</text><text id="targetAttribute">game.attributes.id113566</text><text id="RHS"><expression><string>60+</string><reference keypath="game.attributes.id149397"/></expression></text></attributes></behavior><behavior id="id909389" class="ChangeAttributeAction" enabled="true"><attributes><text id="name">Change Attribute</text><text id="bundleName">ChangeAttribute.behavior</text><text id="targetAttribute">game.attributes.id149397</text><text id="RHS"><expression><reference keypath="game.attributes.id149397"/><string>+5</string></expression></text></attributes></behavior></behaviors><elseBehaviors/></behavior><behavior id="id408707" class="TimerBehavior" enabled="true"><attributes><text id="name">Timer</text><text id="bundleName">Timer.behavior</text><index id="timerType">0</index><real id="interval">1</real><boolean id="runToCompletion">false</boolean></attributes><behaviors><behavior id="id952554" class="ChangeAttributeAction" enabled="true"><attributes><text id="name">Change Attribute</text><text id="bundleName">ChangeAttribute.behavior</text><text id="targetAttribute">game.attributes.id113566</text><text id="RHS"><expression><reference keypath="game.attributes.id113566"/><string>-1</string></expression></text></attributes></behavior></behaviors></behavior></behaviors><aspects><graphics><attributes><boolean id="visible">true</boolean><enumeration id="blendingMode">0</enumeration><enumeration id="horizontalWrap">0</enumeration><enumeration id="verticalWrap">0</enumeration></attributes></graphics><motion><attributes><point id="linearVelocity"><real id="x">0</real><real id="y">0</real></point><real id="angularVelocity">0</real><real id="maxSpeed">0</real><boolean id="applyMaxSpeed">false</boolean></attributes></motion><physics><attributes><real id="density">1</real><real id="friction">3</real><real id="restitution">1</real><boolean id="fixedRotation">false</boolean><boolean id="movable">true</boolean><enumeration id="collisionShape">0</enumeration><real id="drag">0</real><real id="angularDrag">0</real></attributes></physics></aspects></actor>
