<?xml version="1.0" encoding="UTF-8"?>
<game PGFVersion="0.16" GSCVersion="0.9.2" title="Basic Shoot Em Up"><tags>template, tutorial, shmup</tags><resolutionIndependence>0</resolutionIndependence><instructions>Learn how to create this game at
http://gamesalad.com/wiki/tutorials:basic_shoot_em_up</instructions><resolution>0</resolution><longDescription>Shoot anything that moves. You're indestructible! Spaz out!</longDescription><prototypes><actor id="id930615"/><actor id="id926383"/><actor id="id768623"/><actor id="id472900"/><actor id="id794126"/><actor id="id167738"/><actor id="id981838"/><actor id="id751213"/><actor id="id151461"/><actor id="id544776"/><actor id="id779656"/><actor id="id591440"/><actor id="id289207"/><actor id="id846875"/><actor id="id930106"/><actor id="id400679"/><actor id="id272830"/><actor id="id529214"/><actor id="id884432"/><actor id="id593044"/><actor id="id862684"/><actor id="id937862"/><actor id="id261687"/><actor id="id417861"/><actor id="id421376"/><actor id="id557850"/><actor id="id949213"/><actor id="id625653"/><actor id="id359270"/><actor id="id756258"/><actor id="id335564"/><actor id="id233183"/><actor id="id375362"/><actor id="id748659"/><actor id="id167953"/><actor id="id149973"/></prototypes><scenes><scene id="id573736"/><scene id="id623221"/><scene id="id269551"/><scene id="id316680"/><scene id="id586500"/><scene id="id781812"/><scene id="id275271"/><scene id="id182007"/></scenes><attributes><text id="name">default name</text><real id="time">0</real><size id="displaySize"><real id="width">480</real><real id="height">320</real></size><text id="actorTags">Enemy Targets</text><real name="Player X" id="id109120">0</real><real name="Player Y" id="id388541">0</real><boolean name="Game Over" id="id139344">false</boolean><boolean name="Boss Survived" id="id148203">false</boolean><integer name="Score" id="id351029">0</integer><integer name="My Score" id="id478272">0</integer><integer name="Next Level" id="id900668">3</integer><boolean name="Up" id="id228078">false</boolean><boolean name="Down" id="id820345">false</boolean><boolean name="Left" id="id141946">false</boolean><boolean name="Right" id="id390989">false</boolean><boolean name="Shoot" id="id165655">false</boolean></attributes></game>
